README.md
setup.py
udacity_feser_probability/Binomialdistribution.py
udacity_feser_probability/Gaussiandistribution.py
udacity_feser_probability/Generaldistribution.py
udacity_feser_probability/__init__.py
udacity_feser_probability.egg-info/PKG-INFO
udacity_feser_probability.egg-info/SOURCES.txt
udacity_feser_probability.egg-info/dependency_links.txt
udacity_feser_probability.egg-info/not-zip-safe
udacity_feser_probability.egg-info/top_level.txt