Metadata-Version: 1.0
Name: udacity-feser-probability
Version: 0.1
Summary: Gaussian distributions
Home-page: UNKNOWN
Author: Fatih Eser
Author-email: UNKNOWN
License: UNKNOWN
Platform: UNKNOWN
